sphinxcontrib/paverutils.py
sphinxcontrib_paverutils-1.18.1.dist-info/METADATA
sphinxcontrib_paverutils-1.18.1.dist-info/WHEEL
sphinxcontrib_paverutils-1.18.1.dist-info/licenses/LICENSE
sphinxcontrib_paverutils-1.18.1.dist-info/RECORD
