Metadata-Version: 2.4
Name: sphinxcontrib-paverutils
Version: 1.18.1
Summary: Sphinx/Paver integration
Project-URL: Homepage, https://bitbucket.org/dhellmann/sphinxcontrib-paverutils/
Author-email: Doug Hellmann <doug@doughellmann.com>
License-Expression: BSD-2-Clause
License-File: LICENSE
Keywords: documentation,sphinx
Classifier: Development Status :: 5 - Production/Stable
Classifier: Environment :: Console
Classifier: Intended Audience :: Developers
Classifier: License :: OSI Approved :: BSD License
Classifier: Operating System :: OS Independent
Classifier: Programming Language :: Python
Classifier: Programming Language :: Python :: 3
Classifier: Programming Language :: Python :: 3.10
Classifier: Programming Language :: Python :: 3.11
Classifier: Programming Language :: Python :: 3.12
Classifier: Topic :: Documentation
Classifier: Topic :: Utilities
Requires-Dist: paver>=1.02.0
Requires-Dist: sphinx>=1.7.1
Provides-Extra: test
Requires-Dist: ruff; extra == 'test'
